LICENSE.txt
MANIFEST.in
README.md
pyproject.toml
setup.cfg
setup.py
data/data_file
data/package_data.dat
data/test_data.txt
data/usage.txt
src/genomedashboard/__init__.py
src/genomedashboard/cli.py
src/genomedashboard/convert.py
src/genomedashboard/ds.py
src/genomedashboard/io.py
src/genomedashboard/mathfunction.py
src/genomedashboard/data/package_data.dat
src/genomedashboard/data/test_data.txt
src/genomedashboard/data/usage.txt
src/sample/__init__.py
src/ttggdashtest.egg-info/PKG-INFO
src/ttggdashtest.egg-info/SOURCES.txt
src/ttggdashtest.egg-info/dependency_links.txt
src/ttggdashtest.egg-info/entry_points.txt
src/ttggdashtest.egg-info/requires.txt
src/ttggdashtest.egg-info/top_level.txt